[{"id":"4136969620","username":"jawad.hira","type":false,"fbid_v2":"17841404128607121","rest_id":"4346306630","full_name":"Hira Jawad","is_private":true,"post_count":false,"account_type":2.0,"is_unpublished":false,"show_account_transparency_details":true,"profile_picture":"https:\/\/b8fd-2603-3-610c-1060-00.ngrok-free.app\/media\/instagram_profile_pic\/5462dfd4-44d7-4af2-9ca2-b6672dc53aeb.jpg","service":"instagram"},{"id":"4136969620","username":"tabina.malik","type":false,"fbid_v2":"17841404128607121","rest_id":"5688227970","full_name":"Tabina Malik","is_private":true,"post_count":false,"account_type":2.0,"is_unpublished":false,"show_account_transparency_details":true,"profile_picture":"https:\/\/b8fd-2603-3-610c-1060-00.ngrok-free.app\/media\/instagram_profile_pic\/1c772007-d11c-47d9-b77a-f7971df98e7a.jpg","service":"instagram"},{"id":"4136969620","username":"bareerasgram","type":false,"fbid_v2":"17841404128607121","rest_id":"53370256993","full_name":"\ud835\udc01\ud835\udc1a\ud835\udc2b\ud835\udc1e\ud835\udc1e\ud835\udc2b\ud835\udc1a","is_private":true,"post_count":false,"account_type":2.0,"is_unpublished":false,"show_account_transparency_details":true,"profile_picture":"https:\/\/b8fd-2603-3-610c-1060-00.ngrok-free.app\/media\/instagram_profile_pic\/38a89f33-4f3c-4e7d-a737-e31fba080136.jpg","service":"instagram"},{"id":"4136969620","username":"asfand.zahid","type":false,"fbid_v2":"17841404128607121","rest_id":"1523758655","full_name":"\u0627\u0633\u0641\u0646\u062f\u06cc\u0627\u0631\u0632\u0627\u06be\u062f","is_private":true,"post_count":false,"account_type":2.0,"is_unpublished":false,"show_account_transparency_details":true,"profile_picture":"https:\/\/b8fd-2603-3-610c-1060-00.ngrok-free.app\/media\/instagram_profile_pic\/6305ed38-4efa-452d-ad98-803bf875ec7b.jpg","service":"instagram"},{"id":"4136969620","username":"abeersohail08","type":false,"fbid_v2":"17841404128607121","rest_id":"483209254","full_name":"Abeer","is_private":true,"post_count":false,"account_type":2.0,"is_unpublished":false,"show_account_transparency_details":true,"profile_picture":"https:\/\/b8fd-2603-3-610c-1060-00.ngrok-free.app\/media\/instagram_profile_pic\/2512f6be-2f61-406a-9242-4bbfbb643c94.jpg","service":"instagram"},{"id":"4136969620","username":"saniya._.fatima13","type":false,"fbid_v2":"17841404128607121","rest_id":"4679960894","full_name":"Saniya Fatima","is_private":true,"post_count":false,"account_type":2.0,"is_unpublished":false,"show_account_transparency_details":true,"profile_picture":"https:\/\/b8fd-2603-3-610c-1060-00.ngrok-free.app\/media\/instagram_profile_pic\/66bb00b6-1a24-4f42-ae62-862545d6435a.jpg","service":"instagram"},{"id":"4136969620","username":"kanza.chaudhry","type":false,"fbid_v2":"17841404128607121","rest_id":"2010769223","full_name":"Kanza Chaudhry","is_private":true,"post_count":false,"account_type":2.0,"is_unpublished":false,"show_account_transparency_details":true,"profile_picture":"https:\/\/b8fd-2603-3-610c-1060-00.ngrok-free.app\/media\/instagram_profile_pic\/83baecbc-2d26-4701-a573-1da6bbb3dcb6.jpg","service":"instagram"},{"id":"4136969620","username":"zarahussainn","type":false,"fbid_v2":"17841404128607121","rest_id":"3646237476","full_name":"Zara Hussain","is_private":true,"post_count":false,"account_type":2.0,"is_unpublished":false,"show_account_transparency_details":true,"profile_picture":"https:\/\/b8fd-2603-3-610c-1060-00.ngrok-free.app\/media\/instagram_profile_pic\/4963328b-ab55-41c4-8cc0-efc9f370914d.jpg","service":"instagram"},{"id":"4136969620","username":"dawood_malik555","type":false,"fbid_v2":"17841404128607121","rest_id":"1540573190","full_name":"Dawood Malik.","is_private":true,"post_count":false,"account_type":2.0,"is_unpublished":false,"show_account_transparency_details":true,"profile_picture":"https:\/\/b8fd-2603-3-610c-1060-00.ngrok-free.app\/media\/instagram_profile_pic\/550f5f8e-4fb9-45cb-9e80-370cd806961a.jpg","service":"instagram"},{"id":"4136969620","username":"arfajalal","type":false,"fbid_v2":"17841404128607121","rest_id":"3765440121","full_name":"Arfa","is_private":true,"post_count":false,"account_type":2.0,"is_unpublished":false,"show_account_transparency_details":true,"profile_picture":"https:\/\/b8fd-2603-3-610c-1060-00.ngrok-free.app\/media\/instagram_profile_pic\/c96f000d-9341-4e77-942b-bc2955584abf.jpg","service":"instagram"},{"id":"4136969620","username":"reemostat","type":false,"fbid_v2":"17841404128607121","rest_id":"2044893018","full_name":"rayan","is_private":true,"post_count":false,"account_type":2.0,"is_unpublished":false,"show_account_transparency_details":true,"profile_picture":"https:\/\/b8fd-2603-3-610c-1060-00.ngrok-free.app\/media\/instagram_profile_pic\/34ab7ff5-bdd2-40ef-a03e-06373d88f8dc.jpg","service":"instagram"},{"id":"4136969620","username":"amjadshyma","type":false,"fbid_v2":"17841404128607121","rest_id":"5866893563","full_name":"Shyma Amjad","is_private":true,"post_count":false,"account_type":2.0,"is_unpublished":false,"show_account_transparency_details":true,"profile_picture":"https:\/\/b8fd-2603-3-610c-1060-00.ngrok-free.app\/media\/instagram_profile_pic\/2d3892b3-8057-4e54-b990-b76bb2bb0478.jpg","service":"instagram"},{"id":"4136969620","username":"smndipity","type":false,"fbid_v2":"17841404128607121","rest_id":"7304371408","full_name":"","is_private":true,"post_count":false,"account_type":2.0,"is_unpublished":false,"show_account_transparency_details":true,"profile_picture":"https:\/\/b8fd-2603-3-610c-1060-00.ngrok-free.app\/media\/instagram_profile_pic\/7b6f1b21-6f1d-4633-8cb6-efa8aaff2141.jpg","service":"instagram"},{"id":"4136969620","username":"nehl.n","type":false,"fbid_v2":"17841404128607121","rest_id":"1788423129","full_name":"","is_private":true,"post_count":false,"account_type":2.0,"is_unpublished":false,"show_account_transparency_details":true,"profile_picture":"https:\/\/b8fd-2603-3-610c-1060-00.ngrok-free.app\/media\/instagram_profile_pic\/765f2161-b1fe-4eb8-8989-69d690c07767.jpg","service":"instagram"},{"id":"4136969620","username":"anam.waqas","type":false,"fbid_v2":"17841404128607121","rest_id":"1420352892","full_name":"Anum Waqas","is_private":true,"post_count":false,"account_type":2.0,"is_unpublished":false,"show_account_transparency_details":true,"profile_picture":"https:\/\/b8fd-2603-3-610c-1060-00.ngrok-free.app\/media\/instagram_profile_pic\/dad888a7-1fb3-470b-8f92-8c5d54595c1a.jpg","service":"instagram"},{"id":"4136969620","username":"nadia.j.seth","type":false,"fbid_v2":"17841404128607121","rest_id":"2284427099","full_name":"Nadia J. Seth","is_private":true,"post_count":false,"account_type":2.0,"is_unpublished":false,"show_account_transparency_details":true,"profile_picture":"https:\/\/b8fd-2603-3-610c-1060-00.ngrok-free.app\/media\/instagram_profile_pic\/122f04af-207a-41e7-b143-4c4c8a8210dd.jpg","service":"instagram"},{"id":"4136969620","username":"mamoosh181","type":false,"fbid_v2":"17841404128607121","rest_id":"67471360851","full_name":"","is_private":true,"post_count":false,"account_type":2.0,"is_unpublished":false,"show_account_transparency_details":true,"profile_picture":"https:\/\/b8fd-2603-3-610c-1060-00.ngrok-free.app\/media\/instagram_profile_pic\/f6565bcb-5d5c-43d9-8382-bf7d202337b3.jpg","service":"instagram"},{"id":"4136969620","username":"saimafarooq888","type":false,"fbid_v2":"17841404128607121","rest_id":"42800100206","full_name":"Saima Farooq","is_private":true,"post_count":false,"account_type":2.0,"is_unpublished":false,"show_account_transparency_details":true,"profile_picture":"https:\/\/b8fd-2603-3-610c-1060-00.ngrok-free.app\/media\/instagram_profile_pic\/7718ebb6-0ab2-47c3-97cb-457aaca3830a.jpg","service":"instagram"},{"id":"4136969620","username":"mahnoorehan","type":false,"fbid_v2":"17841404128607121","rest_id":"320460232","full_name":"Mahnoor Rehan","is_private":true,"post_count":false,"account_type":2.0,"is_unpublished":false,"show_account_transparency_details":true,"profile_picture":"https:\/\/b8fd-2603-3-610c-1060-00.ngrok-free.app\/media\/instagram_profile_pic\/6e834797-0fd0-4bb7-ba1f-891304f2e9ec.jpg","service":"instagram"},{"id":"4136969620","username":"dina_meoww","type":false,"fbid_v2":"17841404128607121","rest_id":"1397807810","full_name":"Adeena Mushtaq Khatri   *\u0a48\u2729\u2027\u208a\u02da","is_private":false,"post_count":false,"account_type":2.0,"is_unpublished":false,"show_account_transparency_details":true,"profile_picture":"https:\/\/b8fd-2603-3-610c-1060-00.ngrok-free.app\/media\/instagram_profile_pic\/60f5b24e-b9ac-46ee-9b1d-fbf3bb919236.jpg","service":"instagram"},{"id":"4136969620","username":"zainab.shamsiii","type":false,"fbid_v2":"17841404128607121","rest_id":"8924654928","full_name":"Shamsi","is_private":true,"post_count":false,"account_type":2.0,"is_unpublished":false,"show_account_transparency_details":true,"profile_picture":"https:\/\/b8fd-2603-3-610c-1060-00.ngrok-free.app\/media\/instagram_profile_pic\/4ee24578-f642-4aff-811a-1ccbf0703274.jpg","service":"instagram"},{"id":"4136969620","username":"sleepylashta","type":false,"fbid_v2":"17841404128607121","rest_id":"60012654022","full_name":"Lakhta","is_private":false,"post_count":false,"account_type":2.0,"is_unpublished":false,"show_account_transparency_details":true,"profile_picture":"https:\/\/b8fd-2603-3-610c-1060-00.ngrok-free.app\/media\/instagram_profile_pic\/b862762b-b6e0-4819-8e0f-0e98347073b9.jpg","service":"instagram"},{"id":"4136969620","username":"sameera.suhail_","type":false,"fbid_v2":"17841404128607121","rest_id":"4296878334","full_name":"Sameera Suhail","is_private":true,"post_count":false,"account_type":2.0,"is_unpublished":false,"show_account_transparency_details":true,"profile_picture":"https:\/\/b8fd-2603-3-610c-1060-00.ngrok-free.app\/media\/instagram_profile_pic\/7bdd4214-29c1-4df6-a30a-4d7556edf8d7.jpg","service":"instagram"},{"id":"4136969620","username":"riaz.samar","type":false,"fbid_v2":"17841404128607121","rest_id":"3126691114","full_name":"mrs.riaz","is_private":true,"post_count":false,"account_type":2.0,"is_unpublished":false,"show_account_transparency_details":true,"profile_picture":"https:\/\/b8fd-2603-3-610c-1060-00.ngrok-free.app\/media\/instagram_profile_pic\/a281cc51-6e14-4f32-9caf-0c60d0536ce1.jpg","service":"instagram"},{"id":"4136969620","username":"zohasalman11","type":false,"fbid_v2":"17841404128607121","rest_id":"472246994","full_name":"Zoha Salman","is_private":true,"post_count":false,"account_type":2.0,"is_unpublished":false,"show_account_transparency_details":true,"profile_picture":"https:\/\/b8fd-2603-3-610c-1060-00.ngrok-free.app\/media\/instagram_profile_pic\/0fc7a275-8825-479c-9949-2f196c876e25.jpg","service":"instagram"},{"id":"4136969620","username":"empressemano","type":false,"fbid_v2":"17841404128607121","rest_id":"1396478986","full_name":"Eman Omar","is_private":true,"post_count":false,"account_type":2.0,"is_unpublished":false,"show_account_transparency_details":true,"profile_picture":"https:\/\/b8fd-2603-3-610c-1060-00.ngrok-free.app\/media\/instagram_profile_pic\/7988549d-e4c9-4afc-aff8-aa4fd5e6972b.jpg","service":"instagram"},{"id":"4136969620","username":"neha_awaisi","type":false,"fbid_v2":"17841404128607121","rest_id":"1372443641","full_name":"Neha","is_private":true,"post_count":false,"account_type":2.0,"is_unpublished":false,"show_account_transparency_details":true,"profile_picture":"https:\/\/b8fd-2603-3-610c-1060-00.ngrok-free.app\/media\/instagram_profile_pic\/00e4b6d5-196c-46bf-a54c-dbc301165996.jpg","service":"instagram"},{"id":"4136969620","username":"laiba0210","type":false,"fbid_v2":"17841404128607121","rest_id":"352257786","full_name":"Laiba","is_private":true,"post_count":false,"account_type":2.0,"is_unpublished":false,"show_account_transparency_details":true,"profile_picture":"https:\/\/b8fd-2603-3-610c-1060-00.ngrok-free.app\/media\/instagram_profile_pic\/4bb055ed-014b-44dd-ad89-772a4378a65d.jpg","service":"instagram"},{"id":"4136969620","username":"hiraasifofficial","type":false,"fbid_v2":"17841404128607121","rest_id":"59801222841","full_name":"Hira Asif","is_private":false,"post_count":false,"account_type":2.0,"is_unpublished":false,"show_account_transparency_details":true,"profile_picture":"https:\/\/b8fd-2603-3-610c-1060-00.ngrok-free.app\/media\/instagram_profile_pic\/ffa2261e-37c3-4ca8-9b26-4773f77c246f.jpg","service":"instagram"},{"id":"4136969620","username":"zainab_japanwala","type":false,"fbid_v2":"17841404128607121","rest_id":"3868204051","full_name":"Zainab Jawed Japanwala","is_private":true,"post_count":false,"account_type":2.0,"is_unpublished":false,"show_account_transparency_details":true,"profile_picture":"https:\/\/b8fd-2603-3-610c-1060-00.ngrok-free.app\/media\/instagram_profile_pic\/a263d333-06a1-4aaa-8ee3-33f9c3ec2cab.jpg","service":"instagram"},{"id":"4136969620","username":"mida_me","type":false,"fbid_v2":"17841404128607121","rest_id":"45733660786","full_name":"","is_private":true,"post_count":false,"account_type":2.0,"is_unpublished":false,"show_account_transparency_details":true,"profile_picture":"https:\/\/b8fd-2603-3-610c-1060-00.ngrok-free.app\/media\/instagram_profile_pic\/3b23122f-e2dd-4c2e-94f6-95ab824e9c87.jpg","service":"instagram"},{"id":"4136969620","username":"zyneb_m_rehman148","type":false,"fbid_v2":"17841404128607121","rest_id":"13572275627","full_name":"\u0632\u06cc\u0646\u0628.\u0631\u062d\u0645\u0627\u0646","is_private":true,"post_count":false,"account_type":2.0,"is_unpublished":false,"show_account_transparency_details":true,"profile_picture":"https:\/\/b8fd-2603-3-610c-1060-00.ngrok-free.app\/media\/instagram_profile_pic\/73152a69-0240-4e03-99ee-ab3f5478d37a.jpg","service":"instagram"},{"id":"4136969620","username":"meharrshd","type":false,"fbid_v2":"17841404128607121","rest_id":"3284676812","full_name":"Mehr fatima Rasheed","is_private":true,"post_count":false,"account_type":2.0,"is_unpublished":false,"show_account_transparency_details":true,"profile_picture":"https:\/\/b8fd-2603-3-610c-1060-00.ngrok-free.app\/media\/instagram_profile_pic\/f2717b66-14a1-41f9-aefb-b1942f91f43d.jpg","service":"instagram"},{"id":"4136969620","username":"sibtulhasnainashmal","type":false,"fbid_v2":"17841404128607121","rest_id":"5504837144","full_name":"Sibt Ul Hasnain Ashmal","is_private":true,"post_count":false,"account_type":2.0,"is_unpublished":false,"show_account_transparency_details":true,"profile_picture":"https:\/\/b8fd-2603-3-610c-1060-00.ngrok-free.app\/media\/instagram_profile_pic\/d3a6da1a-83d2-4c0a-aeeb-371f64d881ac.jpg","service":"instagram"},{"id":"4136969620","username":"samia.iftikhar.944","type":false,"fbid_v2":"17841404128607121","rest_id":"6917248320","full_name":"Samia Iftikhar","is_private":true,"post_count":false,"account_type":2.0,"is_unpublished":false,"show_account_transparency_details":true,"profile_picture":"https:\/\/b8fd-2603-3-610c-1060-00.ngrok-free.app\/media\/instagram_profile_pic\/57ab923f-5bb5-4776-b17a-6f2e5e428b90.jpg","service":"instagram"},{"id":"4136969620","username":"naba_salahuddin","type":false,"fbid_v2":"17841404128607121","rest_id":"491311020","full_name":"Naba Salahuddin","is_private":true,"post_count":false,"account_type":2.0,"is_unpublished":false,"show_account_transparency_details":true,"profile_picture":"https:\/\/b8fd-2603-3-610c-1060-00.ngrok-free.app\/media\/instagram_profile_pic\/b795d99c-af11-4d99-b14a-d14a18ab56a4.jpg","service":"instagram"},{"id":"4136969620","username":"saraarshad799","type":false,"fbid_v2":"17841404128607121","rest_id":"3236443513","full_name":"","is_private":true,"post_count":false,"account_type":2.0,"is_unpublished":false,"show_account_transparency_details":true,"profile_picture":"https:\/\/b8fd-2603-3-610c-1060-00.ngrok-free.app\/media\/instagram_profile_pic\/de1e02d1-7e9a-4104-9364-a3c97301a46e.jpg","service":"instagram"},{"id":"4136969620","username":"areebaahmed._o","type":false,"fbid_v2":"17841404128607121","rest_id":"1790528190","full_name":"Areeba Ahmed","is_private":true,"post_count":false,"account_type":2.0,"is_unpublished":false,"show_account_transparency_details":true,"profile_picture":"https:\/\/b8fd-2603-3-610c-1060-00.ngrok-free.app\/media\/instagram_profile_pic\/8bb6fd5d-89f1-4fbf-8505-eec1f7bf09a6.jpg","service":"instagram"},{"id":"4136969620","username":"thegemsuite","type":false,"fbid_v2":"17841404128607121","rest_id":"1580512140","full_name":"\ud835\udd4b\ud835\udd59\ud835\udd56 \ud835\udd3e\ud835\udd56\ud835\udd5e \ud835\udd4a\ud835\udd66\ud835\udd5a\ud835\udd65\ud835\udd56 \ud835\udd53\ud835\udd6a \ud835\udd44\ud835\udd52\ud835\udd55\ud835\udd6a\ud835\udd59\ud835\udd52","is_private":false,"post_count":false,"account_type":2.0,"is_unpublished":false,"show_account_transparency_details":true,"profile_picture":"https:\/\/b8fd-2603-3-610c-1060-00.ngrok-free.app\/media\/instagram_profile_pic\/a317cf67-7ccd-4a5c-8f9c-98feec37cc0f.jpg","service":"instagram"},{"id":"4136969620","username":"fizzah_ch","type":false,"fbid_v2":"17841404128607121","rest_id":"1685144612","full_name":"\u0641\u0636\u0647 \u0634\u0627\u062d\u062f","is_private":true,"post_count":false,"account_type":2.0,"is_unpublished":false,"show_account_transparency_details":true,"profile_picture":"https:\/\/b8fd-2603-3-610c-1060-00.ngrok-free.app\/media\/instagram_profile_pic\/807f3efa-6668-4f72-93f8-b6ce1fceef32.jpg","service":"instagram"},{"id":"4136969620","username":"beenishzahid","type":false,"fbid_v2":"17841404128607121","rest_id":"176550177","full_name":"Beenish Zahid","is_private":true,"post_count":false,"account_type":2.0,"is_unpublished":false,"show_account_transparency_details":true,"profile_picture":"https:\/\/b8fd-2603-3-610c-1060-00.ngrok-free.app\/media\/instagram_profile_pic\/5adddfaa-760a-49b4-bdfe-58d10d703d51.jpg","service":"instagram"},{"id":"4136969620","username":"fidaudii","type":false,"fbid_v2":"17841404128607121","rest_id":"25210374354","full_name":"Farwah Imran","is_private":true,"post_count":false,"account_type":2.0,"is_unpublished":false,"show_account_transparency_details":true,"profile_picture":"https:\/\/b8fd-2603-3-610c-1060-00.ngrok-free.app\/media\/instagram_profile_pic\/1f938b64-bb78-4b89-af8d-6a66f8ecd966.jpg","service":"instagram"},{"id":"4136969620","username":"anum.ahmed","type":false,"fbid_v2":"17841404128607121","rest_id":"1545208113","full_name":"A n u m    A h m e d","is_private":true,"post_count":false,"account_type":2.0,"is_unpublished":false,"show_account_transparency_details":true,"profile_picture":"https:\/\/b8fd-2603-3-610c-1060-00.ngrok-free.app\/media\/instagram_profile_pic\/ac977fea-aaf7-4436-a139-6845c01eacd8.jpg","service":"instagram"},{"id":"4136969620","username":"iobaid27","type":false,"fbid_v2":"17841404128607121","rest_id":"38209680182","full_name":"Jeena Obaid Khan","is_private":true,"post_count":false,"account_type":2.0,"is_unpublished":false,"show_account_transparency_details":true,"profile_picture":"https:\/\/b8fd-2603-3-610c-1060-00.ngrok-free.app\/media\/instagram_profile_pic\/efd98068-1a36-49b5-bf30-580a26bbe8e1.jpg","service":"instagram"},{"id":"4136969620","username":"ezzahfatimaa1","type":false,"fbid_v2":"17841404128607121","rest_id":"47633070476","full_name":"Ezzah","is_private":true,"post_count":false,"account_type":2.0,"is_unpublished":false,"show_account_transparency_details":true,"profile_picture":"https:\/\/b8fd-2603-3-610c-1060-00.ngrok-free.app\/media\/instagram_profile_pic\/dd61a1e8-4979-4568-9435-b72535bb5f28.jpg","service":"instagram"},{"id":"4136969620","username":"amnaatahir2011","type":false,"fbid_v2":"17841404128607121","rest_id":"3100031445","full_name":"Amna Tahir","is_private":true,"post_count":false,"account_type":2.0,"is_unpublished":false,"show_account_transparency_details":true,"profile_picture":"https:\/\/b8fd-2603-3-610c-1060-00.ngrok-free.app\/media\/instagram_profile_pic\/f28e5e5c-b746-4a7f-8640-60cf229d4a18.jpg","service":"instagram"},{"id":"4136969620","username":"mahn0oor","type":false,"fbid_v2":"17841404128607121","rest_id":"976657866","full_name":"Mahnoor Shahid","is_private":true,"post_count":false,"account_type":2.0,"is_unpublished":false,"show_account_transparency_details":true,"profile_picture":"https:\/\/b8fd-2603-3-610c-1060-00.ngrok-free.app\/media\/instagram_profile_pic\/b968b818-2ab9-49d0-8ba5-349488bebf7e.jpg","service":"instagram"},{"id":"4136969620","username":"_hamnarizwanbutt","type":false,"fbid_v2":"17841404128607121","rest_id":"1626780182","full_name":"Hamna A. Rizwan","is_private":true,"post_count":false,"account_type":2.0,"is_unpublished":false,"show_account_transparency_details":true,"profile_picture":"https:\/\/b8fd-2603-3-610c-1060-00.ngrok-free.app\/media\/instagram_profile_pic\/f5f9d9d3-cbb4-4c04-af82-3d6e7179443b.jpg","service":"instagram"},{"id":"4136969620","username":"ayraaay_","type":false,"fbid_v2":"17841404128607121","rest_id":"16096432834","full_name":"ayra","is_private":true,"post_count":false,"account_type":2.0,"is_unpublished":false,"show_account_transparency_details":true,"profile_picture":"https:\/\/b8fd-2603-3-610c-1060-00.ngrok-free.app\/media\/instagram_profile_pic\/4682965a-d052-4bf6-8629-14610b532194.jpg","service":"instagram"},{"id":"4136969620","username":"kashmine_hanif","type":false,"fbid_v2":"17841404128607121","rest_id":"3461265671","full_name":"","is_private":true,"post_count":false,"account_type":2.0,"is_unpublished":false,"show_account_transparency_details":true,"profile_picture":"https:\/\/b8fd-2603-3-610c-1060-00.ngrok-free.app\/media\/instagram_profile_pic\/a87ce3b1-79a3-4306-8546-1c8d7062b0dc.jpg","service":"instagram"}]