[{"id":"4136969620","username":"anaaidreesqureshi","type":false,"fbid_v2":"17841404128607121","rest_id":"4984430636","full_name":"NesM | TRAVEL","is_private":false,"post_count":false,"account_type":2.0,"is_unpublished":false,"show_account_transparency_details":true,"profile_picture":"https:\/\/b8fd-2603-3-610c-1060-00.ngrok-free.app\/media\/instagram_profile_pic\/f76791b5-8e02-4033-b267-2a566671ae50.jpg","service":"instagram"},{"id":"4136969620","username":"sunflowerfishie","type":false,"fbid_v2":"17841404128607121","rest_id":"63984291867","full_name":"NesM | TRAVEL","is_private":true,"post_count":false,"account_type":2.0,"is_unpublished":false,"show_account_transparency_details":true,"profile_picture":"https:\/\/b8fd-2603-3-610c-1060-00.ngrok-free.app\/media\/instagram_profile_pic\/9736ddaf-617a-4580-ad45-80243d66f8d3.jpg","service":"instagram"},{"id":"4136969620","username":"hania_kanwal1","type":false,"fbid_v2":"17841404128607121","rest_id":"39653057965","full_name":"NesM | TRAVEL","is_private":true,"post_count":false,"account_type":2.0,"is_unpublished":false,"show_account_transparency_details":true,"profile_picture":"https:\/\/b8fd-2603-3-610c-1060-00.ngrok-free.app\/media\/instagram_profile_pic\/397a65e0-0aa9-4dbc-b06c-929d2679fd52.jpg","service":"instagram"},{"id":"4136969620","username":"fatima.a.zamani","type":false,"fbid_v2":"17841404128607121","rest_id":"1913490257","full_name":"NesM | TRAVEL","is_private":true,"post_count":false,"account_type":2.0,"is_unpublished":false,"show_account_transparency_details":true,"profile_picture":"https:\/\/b8fd-2603-3-610c-1060-00.ngrok-free.app\/media\/instagram_profile_pic\/7b880b3b-c241-474c-83d4-535663325f4a.jpg","service":"instagram"},{"id":"4136969620","username":"taimurelahi","type":false,"fbid_v2":"17841404128607121","rest_id":"260173949","full_name":"NesM | TRAVEL","is_private":true,"post_count":false,"account_type":2.0,"is_unpublished":false,"show_account_transparency_details":true,"profile_picture":"https:\/\/b8fd-2603-3-610c-1060-00.ngrok-free.app\/media\/instagram_profile_pic\/31e14d70-bc87-4d5a-934a-cb95162551f2.jpg","service":"instagram"},{"id":"4136969620","username":"salehakhan12","type":false,"fbid_v2":"17841404128607121","rest_id":"318862325","full_name":"NesM | TRAVEL","is_private":false,"post_count":false,"account_type":2.0,"is_unpublished":false,"show_account_transparency_details":true,"profile_picture":"https:\/\/b8fd-2603-3-610c-1060-00.ngrok-free.app\/media\/instagram_profile_pic\/1f66fc5a-5f35-4fd1-a7a5-dd699d50dd91.jpg","service":"instagram"},{"id":"4136969620","username":"mysa.pst","type":false,"fbid_v2":"17841404128607121","rest_id":"61176052689","full_name":"NesM | TRAVEL","is_private":false,"post_count":false,"account_type":2.0,"is_unpublished":false,"show_account_transparency_details":true,"profile_picture":"https:\/\/b8fd-2603-3-610c-1060-00.ngrok-free.app\/media\/instagram_profile_pic\/95d7577d-e76d-4638-9357-63403335f51a.jpg","service":"instagram"},{"id":"4136969620","username":"saadsaqib_1","type":false,"fbid_v2":"17841404128607121","rest_id":"33601611034","full_name":"NesM | TRAVEL","is_private":true,"post_count":false,"account_type":2.0,"is_unpublished":false,"show_account_transparency_details":true,"profile_picture":"https:\/\/b8fd-2603-3-610c-1060-00.ngrok-free.app\/media\/instagram_profile_pic\/1a61be54-4d85-44c3-a405-bf7350dfde3b.jpg","service":"instagram"},{"id":"4136969620","username":"malihakhalid123","type":false,"fbid_v2":"17841404128607121","rest_id":"7886353928","full_name":"NesM | TRAVEL","is_private":true,"post_count":false,"account_type":2.0,"is_unpublished":false,"show_account_transparency_details":true,"profile_picture":"https:\/\/b8fd-2603-3-610c-1060-00.ngrok-free.app\/media\/instagram_profile_pic\/29ee6377-d53d-4ec9-8f2d-4a623a11960d.jpg","service":"instagram"},{"id":"4136969620","username":"minaafzalsiraj","type":false,"fbid_v2":"17841404128607121","rest_id":"340049258","full_name":"NesM | TRAVEL","is_private":true,"post_count":false,"account_type":2.0,"is_unpublished":false,"show_account_transparency_details":true,"profile_picture":"https:\/\/b8fd-2603-3-610c-1060-00.ngrok-free.app\/media\/instagram_profile_pic\/4bce3047-129a-40ae-a8e6-e1c6e98acdc4.jpg","service":"instagram"},{"id":"4136969620","username":"hibaetc","type":false,"fbid_v2":"17841404128607121","rest_id":"44261711166","full_name":"NesM | TRAVEL","is_private":true,"post_count":false,"account_type":2.0,"is_unpublished":false,"show_account_transparency_details":true,"profile_picture":"https:\/\/b8fd-2603-3-610c-1060-00.ngrok-free.app\/media\/instagram_profile_pic\/3d170ce3-ce10-4f2f-ad74-71030f60f33b.jpg","service":"instagram"},{"id":"4136969620","username":"muhiba.sajjad","type":false,"fbid_v2":"17841404128607121","rest_id":"3638630722","full_name":"NesM | TRAVEL","is_private":true,"post_count":false,"account_type":2.0,"is_unpublished":false,"show_account_transparency_details":true,"profile_picture":"https:\/\/b8fd-2603-3-610c-1060-00.ngrok-free.app\/media\/instagram_profile_pic\/d6b186bf-13d5-4981-8302-8454bc93b2ba.jpg","service":"instagram"},{"id":"4136969620","username":"blogs_by_jia","type":false,"fbid_v2":"17841404128607121","rest_id":"8710656582","full_name":"NesM | TRAVEL","is_private":true,"post_count":false,"account_type":2.0,"is_unpublished":false,"show_account_transparency_details":true,"profile_picture":"https:\/\/b8fd-2603-3-610c-1060-00.ngrok-free.app\/media\/instagram_profile_pic\/683e5840-d041-4dcd-8f9c-0eb6ea4f342b.jpg","service":"instagram"},{"id":"4136969620","username":"sobia289","type":false,"fbid_v2":"17841404128607121","rest_id":"5948295435","full_name":"NesM | TRAVEL","is_private":true,"post_count":false,"account_type":2.0,"is_unpublished":false,"show_account_transparency_details":true,"profile_picture":"https:\/\/b8fd-2603-3-610c-1060-00.ngrok-free.app\/media\/instagram_profile_pic\/76195902-f752-4f55-9f68-4efe0ed5dbfe.jpg","service":"instagram"},{"id":"4136969620","username":"amina.beg","type":false,"fbid_v2":"17841404128607121","rest_id":"2045325225","full_name":"NesM | TRAVEL","is_private":true,"post_count":false,"account_type":2.0,"is_unpublished":false,"show_account_transparency_details":true,"profile_picture":"https:\/\/b8fd-2603-3-610c-1060-00.ngrok-free.app\/media\/instagram_profile_pic\/85984a34-1f1f-4e05-b84a-eaeda0561fab.jpg","service":"instagram"},{"id":"4136969620","username":"hmzaislam_","type":false,"fbid_v2":"17841404128607121","rest_id":"50250686793","full_name":"NesM | TRAVEL","is_private":true,"post_count":false,"account_type":2.0,"is_unpublished":false,"show_account_transparency_details":true,"profile_picture":"https:\/\/b8fd-2603-3-610c-1060-00.ngrok-free.app\/media\/instagram_profile_pic\/a3da4a89-a883-4e64-a1e3-206c62970c5b.jpg","service":"instagram"},{"id":"4136969620","username":"r3mail.priv","type":false,"fbid_v2":"17841404128607121","rest_id":"52179858450","full_name":"NesM | TRAVEL","is_private":true,"post_count":false,"account_type":2.0,"is_unpublished":false,"show_account_transparency_details":true,"profile_picture":"https:\/\/b8fd-2603-3-610c-1060-00.ngrok-free.app\/media\/instagram_profile_pic\/edbfd996-dc8b-47a2-bdae-28a120c9cce2.jpg","service":"instagram"},{"id":"4136969620","username":"mahrukhbukhari","type":false,"fbid_v2":"17841404128607121","rest_id":"340249008","full_name":"NesM | TRAVEL","is_private":true,"post_count":false,"account_type":2.0,"is_unpublished":false,"show_account_transparency_details":true,"profile_picture":"https:\/\/b8fd-2603-3-610c-1060-00.ngrok-free.app\/media\/instagram_profile_pic\/e5523107-e695-4c43-acd8-c8f3490567e8.jpg","service":"instagram"},{"id":"4136969620","username":"areeba0261","type":false,"fbid_v2":"17841404128607121","rest_id":"65908068591","full_name":"NesM | TRAVEL","is_private":true,"post_count":false,"account_type":2.0,"is_unpublished":false,"show_account_transparency_details":true,"profile_picture":"https:\/\/b8fd-2603-3-610c-1060-00.ngrok-free.app\/media\/instagram_profile_pic\/b832ec78-666e-460a-baa3-f4b077229e2c.jpg","service":"instagram"},{"id":"4136969620","username":"khizrajy","type":false,"fbid_v2":"17841404128607121","rest_id":"376804892","full_name":"NesM | TRAVEL","is_private":true,"post_count":false,"account_type":2.0,"is_unpublished":false,"show_account_transparency_details":true,"profile_picture":"https:\/\/b8fd-2603-3-610c-1060-00.ngrok-free.app\/media\/instagram_profile_pic\/031816f4-a687-4aa1-907a-7a5e158ae0f7.jpg","service":"instagram"},{"id":"4136969620","username":"tanshatastic","type":false,"fbid_v2":"17841404128607121","rest_id":"895962311","full_name":"NesM | TRAVEL","is_private":true,"post_count":false,"account_type":2.0,"is_unpublished":false,"show_account_transparency_details":true,"profile_picture":"https:\/\/b8fd-2603-3-610c-1060-00.ngrok-free.app\/media\/instagram_profile_pic\/34d8a0f3-a388-4847-9ccf-d2d95316c115.jpg","service":"instagram"},{"id":"4136969620","username":"hafsa_alabbasi","type":false,"fbid_v2":"17841404128607121","rest_id":"5898755249","full_name":"NesM | TRAVEL","is_private":true,"post_count":false,"account_type":2.0,"is_unpublished":false,"show_account_transparency_details":true,"profile_picture":"https:\/\/b8fd-2603-3-610c-1060-00.ngrok-free.app\/media\/instagram_profile_pic\/5fcb7afb-71f5-49ba-9d54-ba8d90f0a2a1.jpg","service":"instagram"},{"id":"4136969620","username":"malaikanadeem_","type":false,"fbid_v2":"17841404128607121","rest_id":"4387996692","full_name":"NesM | TRAVEL","is_private":true,"post_count":false,"account_type":2.0,"is_unpublished":false,"show_account_transparency_details":true,"profile_picture":"https:\/\/b8fd-2603-3-610c-1060-00.ngrok-free.app\/media\/instagram_profile_pic\/f1eafe41-847a-45f5-9a2f-c1150ce781e5.jpg","service":"instagram"},{"id":"4136969620","username":"safahehsan2224","type":false,"fbid_v2":"17841404128607121","rest_id":"51082668465","full_name":"NesM | TRAVEL","is_private":true,"post_count":false,"account_type":2.0,"is_unpublished":false,"show_account_transparency_details":true,"profile_picture":"https:\/\/b8fd-2603-3-610c-1060-00.ngrok-free.app\/media\/instagram_profile_pic\/ed12a939-593b-41a8-a904-1df1b2d403c7.jpg","service":"instagram"},{"id":"4136969620","username":"maryam.q2004","type":false,"fbid_v2":"17841404128607121","rest_id":"12825500452","full_name":"NesM | TRAVEL","is_private":true,"post_count":false,"account_type":2.0,"is_unpublished":false,"show_account_transparency_details":true,"profile_picture":"https:\/\/b8fd-2603-3-610c-1060-00.ngrok-free.app\/media\/instagram_profile_pic\/2e322372-c04a-4cdc-ad3c-1f40c4e37f1c.jpg","service":"instagram"},{"id":"4136969620","username":"madihajunaiidkh","type":false,"fbid_v2":"17841404128607121","rest_id":"1805134798","full_name":"NesM | TRAVEL","is_private":true,"post_count":false,"account_type":2.0,"is_unpublished":false,"show_account_transparency_details":true,"profile_picture":"https:\/\/b8fd-2603-3-610c-1060-00.ngrok-free.app\/media\/instagram_profile_pic\/e52d9e48-42d5-48a6-940e-4ddc9ec0d6a4.jpg","service":"instagram"},{"id":"4136969620","username":"sehrbutt","type":false,"fbid_v2":"17841404128607121","rest_id":"374653052","full_name":"NesM | TRAVEL","is_private":true,"post_count":false,"account_type":2.0,"is_unpublished":false,"show_account_transparency_details":true,"profile_picture":"https:\/\/b8fd-2603-3-610c-1060-00.ngrok-free.app\/media\/instagram_profile_pic\/fd1aea50-0ac1-4afa-8afb-6727aad27f9f.jpg","service":"instagram"},{"id":"4136969620","username":"armeen9351","type":false,"fbid_v2":"17841404128607121","rest_id":"47699349043","full_name":"NesM | TRAVEL","is_private":true,"post_count":false,"account_type":2.0,"is_unpublished":false,"show_account_transparency_details":true,"profile_picture":"https:\/\/b8fd-2603-3-610c-1060-00.ngrok-free.app\/media\/instagram_profile_pic\/9828036a-3d68-4fbb-9ed2-c52d1007e660.jpg","service":"instagram"},{"id":"4136969620","username":"aabishijazch","type":false,"fbid_v2":"17841404128607121","rest_id":"53384437131","full_name":"NesM | TRAVEL","is_private":true,"post_count":false,"account_type":2.0,"is_unpublished":false,"show_account_transparency_details":true,"profile_picture":"https:\/\/b8fd-2603-3-610c-1060-00.ngrok-free.app\/media\/instagram_profile_pic\/21a141ad-34bf-4fee-b30a-eef4b2c36d32.jpg","service":"instagram"},{"id":"4136969620","username":"nazishamer","type":false,"fbid_v2":"17841404128607121","rest_id":"1216461475","full_name":"NesM | TRAVEL","is_private":true,"post_count":false,"account_type":2.0,"is_unpublished":false,"show_account_transparency_details":true,"profile_picture":"https:\/\/b8fd-2603-3-610c-1060-00.ngrok-free.app\/media\/instagram_profile_pic\/a6a806cd-5f1f-4c59-890f-d594ea432806.jpg","service":"instagram"},{"id":"4136969620","username":"issrarsarah","type":false,"fbid_v2":"17841404128607121","rest_id":"276460287","full_name":"NesM | TRAVEL","is_private":true,"post_count":false,"account_type":2.0,"is_unpublished":false,"show_account_transparency_details":true,"profile_picture":"https:\/\/b8fd-2603-3-610c-1060-00.ngrok-free.app\/media\/instagram_profile_pic\/27937d2b-d29f-46a6-897c-e1b5b11e9c19.jpg","service":"instagram"},{"id":"4136969620","username":"saadiyaloya","type":false,"fbid_v2":"17841404128607121","rest_id":"3028049368","full_name":"NesM | TRAVEL","is_private":true,"post_count":false,"account_type":2.0,"is_unpublished":false,"show_account_transparency_details":true,"profile_picture":"https:\/\/b8fd-2603-3-610c-1060-00.ngrok-free.app\/media\/instagram_profile_pic\/47e8fac6-1423-4e45-9367-1f1356c80560.jpg","service":"instagram"},{"id":"4136969620","username":"hinakzm","type":false,"fbid_v2":"17841404128607121","rest_id":"4793209202","full_name":"NesM | TRAVEL","is_private":true,"post_count":false,"account_type":2.0,"is_unpublished":false,"show_account_transparency_details":true,"profile_picture":"https:\/\/b8fd-2603-3-610c-1060-00.ngrok-free.app\/media\/instagram_profile_pic\/05743829-3c88-4a0c-9792-316b0773dd1e.jpg","service":"instagram"},{"id":"4136969620","username":"ch3rrycokegirl","type":false,"fbid_v2":"17841404128607121","rest_id":"42399735192","full_name":"NesM | TRAVEL","is_private":true,"post_count":false,"account_type":2.0,"is_unpublished":false,"show_account_transparency_details":true,"profile_picture":"https:\/\/b8fd-2603-3-610c-1060-00.ngrok-free.app\/media\/instagram_profile_pic\/549e911e-4c0b-48e7-9e94-fb9b1dd573bd.jpg","service":"instagram"},{"id":"4136969620","username":"aks_me5","type":false,"fbid_v2":"17841404128607121","rest_id":"2260108146","full_name":"NesM | TRAVEL","is_private":false,"post_count":false,"account_type":2.0,"is_unpublished":false,"show_account_transparency_details":true,"profile_picture":"https:\/\/b8fd-2603-3-610c-1060-00.ngrok-free.app\/media\/instagram_profile_pic\/352a98a6-f2b1-4db6-af56-fb182a2a6071.jpg","service":"instagram"},{"id":"4136969620","username":"bisma.ladhubhai","type":false,"fbid_v2":"17841404128607121","rest_id":"64213842655","full_name":"NesM | TRAVEL","is_private":true,"post_count":false,"account_type":2.0,"is_unpublished":false,"show_account_transparency_details":true,"profile_picture":"https:\/\/b8fd-2603-3-610c-1060-00.ngrok-free.app\/media\/instagram_profile_pic\/151bf9f6-7f87-428d-912c-d05c189f934d.jpg","service":"instagram"},{"id":"4136969620","username":"thisisbushra","type":false,"fbid_v2":"17841404128607121","rest_id":"402842947","full_name":"NesM | TRAVEL","is_private":true,"post_count":false,"account_type":2.0,"is_unpublished":false,"show_account_transparency_details":true,"profile_picture":"https:\/\/b8fd-2603-3-610c-1060-00.ngrok-free.app\/media\/instagram_profile_pic\/cbadd0d8-b366-4dcc-bcb5-82f86d164380.jpg","service":"instagram"},{"id":"4136969620","username":"ashooo_95","type":false,"fbid_v2":"17841404128607121","rest_id":"13021008209","full_name":"NesM | TRAVEL","is_private":true,"post_count":false,"account_type":2.0,"is_unpublished":false,"show_account_transparency_details":true,"profile_picture":"https:\/\/b8fd-2603-3-610c-1060-00.ngrok-free.app\/media\/instagram_profile_pic\/fc13c07b-a774-47c9-8611-e980fa499fd5.jpg","service":"instagram"},{"id":"4136969620","username":"taliaqaiser","type":false,"fbid_v2":"17841404128607121","rest_id":"577523800","full_name":"NesM | TRAVEL","is_private":true,"post_count":false,"account_type":2.0,"is_unpublished":false,"show_account_transparency_details":true,"profile_picture":"https:\/\/b8fd-2603-3-610c-1060-00.ngrok-free.app\/media\/instagram_profile_pic\/834988e2-7f99-4d6a-b9fd-7be755106d0a.jpg","service":"instagram"},{"id":"4136969620","username":"ambeenee","type":false,"fbid_v2":"17841404128607121","rest_id":"199911166","full_name":"NesM | TRAVEL","is_private":true,"post_count":false,"account_type":2.0,"is_unpublished":false,"show_account_transparency_details":true,"profile_picture":"https:\/\/b8fd-2603-3-610c-1060-00.ngrok-free.app\/media\/instagram_profile_pic\/202bbcc7-4a6e-4832-80e9-f56d05a6b8c2.jpg","service":"instagram"},{"id":"4136969620","username":"anniiee_walid696","type":false,"fbid_v2":"17841404128607121","rest_id":"5495722030","full_name":"NesM | TRAVEL","is_private":true,"post_count":false,"account_type":2.0,"is_unpublished":false,"show_account_transparency_details":true,"profile_picture":"https:\/\/b8fd-2603-3-610c-1060-00.ngrok-free.app\/media\/instagram_profile_pic\/bbc0bd0b-2f67-42e4-8e72-ba367b722d42.jpg","service":"instagram"},{"id":"4136969620","username":"hira_yasir7","type":false,"fbid_v2":"17841404128607121","rest_id":"1414596258","full_name":"NesM | TRAVEL","is_private":true,"post_count":false,"account_type":2.0,"is_unpublished":false,"show_account_transparency_details":true,"profile_picture":"https:\/\/b8fd-2603-3-610c-1060-00.ngrok-free.app\/media\/instagram_profile_pic\/21759064-8b0c-4fc0-9025-61b9a1727f67.jpg","service":"instagram"},{"id":"4136969620","username":"kiranidrees61","type":false,"fbid_v2":"17841404128607121","rest_id":"18085959103","full_name":"NesM | TRAVEL","is_private":true,"post_count":false,"account_type":2.0,"is_unpublished":false,"show_account_transparency_details":true,"profile_picture":"https:\/\/b8fd-2603-3-610c-1060-00.ngrok-free.app\/media\/instagram_profile_pic\/5eb02110-101a-4a0c-bacd-7a18f33c2f9c.jpg","service":"instagram"},{"id":"4136969620","username":"halimashehryar","type":false,"fbid_v2":"17841404128607121","rest_id":"1708126467","full_name":"NesM | TRAVEL","is_private":true,"post_count":false,"account_type":2.0,"is_unpublished":false,"show_account_transparency_details":true,"profile_picture":"https:\/\/b8fd-2603-3-610c-1060-00.ngrok-free.app\/media\/instagram_profile_pic\/52d5390a-7faa-4b70-a3bd-58957f4e0adf.jpg","service":"instagram"},{"id":"4136969620","username":"a_noor2293","type":false,"fbid_v2":"17841404128607121","rest_id":"53911068450","full_name":"NesM | TRAVEL","is_private":true,"post_count":false,"account_type":2.0,"is_unpublished":false,"show_account_transparency_details":true,"profile_picture":"https:\/\/b8fd-2603-3-610c-1060-00.ngrok-free.app\/media\/instagram_profile_pic\/75d5dc76-d5aa-43f0-85a9-0db78e946ded.jpg","service":"instagram"},{"id":"4136969620","username":"themakeupbaeee","type":false,"fbid_v2":"17841404128607121","rest_id":"8444012942","full_name":"NesM | TRAVEL","is_private":false,"post_count":false,"account_type":2.0,"is_unpublished":false,"show_account_transparency_details":true,"profile_picture":"https:\/\/b8fd-2603-3-610c-1060-00.ngrok-free.app\/media\/instagram_profile_pic\/517069ec-7590-4213-a4b1-49863b7ae6d4.jpg","service":"instagram"},{"id":"4136969620","username":"maham_r91","type":false,"fbid_v2":"17841404128607121","rest_id":"226957970","full_name":"NesM | TRAVEL","is_private":true,"post_count":false,"account_type":2.0,"is_unpublished":false,"show_account_transparency_details":true,"profile_picture":"https:\/\/b8fd-2603-3-610c-1060-00.ngrok-free.app\/media\/instagram_profile_pic\/185cb012-2058-48b0-ad32-e4b5945ba446.jpg","service":"instagram"},{"id":"4136969620","username":"komal.kausar","type":false,"fbid_v2":"17841404128607121","rest_id":"178172315","full_name":"NesM | TRAVEL","is_private":true,"post_count":false,"account_type":2.0,"is_unpublished":false,"show_account_transparency_details":true,"profile_picture":"https:\/\/b8fd-2603-3-610c-1060-00.ngrok-free.app\/media\/instagram_profile_pic\/970ebcb5-b997-4ea3-97f3-d57c1fafe920.jpg","service":"instagram"},{"id":"4136969620","username":"f.naeem08","type":false,"fbid_v2":"17841404128607121","rest_id":"1451862999","full_name":"NesM | TRAVEL","is_private":true,"post_count":false,"account_type":2.0,"is_unpublished":false,"show_account_transparency_details":true,"profile_picture":"https:\/\/b8fd-2603-3-610c-1060-00.ngrok-free.app\/media\/instagram_profile_pic\/e560c69a-c2ba-4a21-adf0-ac5ddddda508.jpg","service":"instagram"},{"id":"4136969620","username":"nida_r89","type":false,"fbid_v2":"17841404128607121","rest_id":"509770479","full_name":"NesM | TRAVEL","is_private":true,"post_count":false,"account_type":2.0,"is_unpublished":false,"show_account_transparency_details":true,"profile_picture":"https:\/\/b8fd-2603-3-610c-1060-00.ngrok-free.app\/media\/instagram_profile_pic\/8c6e329b-26a1-4f5d-b905-3305de4cd370.jpg","service":"instagram"}]