[{"id":"1682023762","username":"seherumar9","type":false,"fbid_v2":"17841401192886281","rest_id":"49345149659","full_name":"Seher Usman","is_private":true,"post_count":false,"is_unpublished":false,"profile_picture":"https:\/\/b8fd-2603-3-610c-1060-00.ngrok-free.app\/media\/instagram_profile_pic\/b90302b9-94ca-47da-994e-20a9bf7b1a70.jpg","show_account_transparency_details":true,"service":"instagram"},{"id":"1682023762","username":"ashworld_2022","type":false,"fbid_v2":"17841401192886281","rest_id":"10830661","full_name":"Ayesha","is_private":true,"post_count":false,"is_unpublished":false,"profile_picture":"https:\/\/b8fd-2603-3-610c-1060-00.ngrok-free.app\/media\/instagram_profile_pic\/26702252-080e-4b20-8a5b-6c5d6a2fe186.jpg","show_account_transparency_details":true,"service":"instagram"},{"id":"1682023762","username":"zainabumair3074","type":false,"fbid_v2":"17841401192886281","rest_id":"7009446599","full_name":"Zainab Umair","is_private":true,"post_count":false,"is_unpublished":false,"profile_picture":"https:\/\/b8fd-2603-3-610c-1060-00.ngrok-free.app\/media\/instagram_profile_pic\/9c8c4d20-4dce-4831-bad8-af79a392f293.jpg","show_account_transparency_details":true,"service":"instagram"},{"id":"1682023762","username":"josh.social","type":false,"fbid_v2":"17841401192886281","rest_id":"5051717643","full_name":"josh.social","is_private":false,"post_count":false,"is_unpublished":false,"profile_picture":"https:\/\/b8fd-2603-3-610c-1060-00.ngrok-free.app\/media\/instagram_profile_pic\/b1e29e39-7e3d-4a30-ac45-21a07027c23f.jpg","show_account_transparency_details":true,"service":"instagram"},{"id":"1682023762","username":"khadijamudassirr","type":false,"fbid_v2":"17841401192886281","rest_id":"7910030113","full_name":"Khadija Mudassir","is_private":true,"post_count":false,"is_unpublished":false,"profile_picture":"https:\/\/b8fd-2603-3-610c-1060-00.ngrok-free.app\/media\/instagram_profile_pic\/37bd1e18-1afe-4dd7-a47b-941601a25fcb.jpg","show_account_transparency_details":true,"service":"instagram"},{"id":"1682023762","username":"manahil_owais547","type":false,"fbid_v2":"17841401192886281","rest_id":"6181517012","full_name":"Manahil Owais","is_private":true,"post_count":false,"is_unpublished":false,"profile_picture":"https:\/\/b8fd-2603-3-610c-1060-00.ngrok-free.app\/media\/instagram_profile_pic\/015b2253-7036-4df1-9c26-1f20d6770ff6.jpg","show_account_transparency_details":true,"service":"instagram"},{"id":"1682023762","username":"2024att","type":false,"fbid_v2":"17841401192886281","rest_id":"6696485831","full_name":"Attiqa\ud83c\udf42","is_private":true,"post_count":false,"is_unpublished":false,"profile_picture":"https:\/\/b8fd-2603-3-610c-1060-00.ngrok-free.app\/media\/instagram_profile_pic\/26fa0fee-0ed9-4c9e-9807-d32250f45feb.jpg","show_account_transparency_details":true,"service":"instagram"},{"id":"1682023762","username":"ange.langel5659","type":false,"fbid_v2":"17841401192886281","rest_id":"60863814557","full_name":"Annistatic","is_private":false,"post_count":false,"is_unpublished":false,"profile_picture":"https:\/\/b8fd-2603-3-610c-1060-00.ngrok-free.app\/media\/instagram_profile_pic\/2e6942cf-4d51-4980-9f9f-05b545096d57.jpg","show_account_transparency_details":true,"service":"instagram"},{"id":"1682023762","username":"sabanaveed04","type":false,"fbid_v2":"17841401192886281","rest_id":"1399337716","full_name":"saba naveed","is_private":true,"post_count":false,"is_unpublished":false,"profile_picture":"https:\/\/b8fd-2603-3-610c-1060-00.ngrok-free.app\/media\/instagram_profile_pic\/ef499228-b13f-4a1b-ac4c-9a757cb5b1e4.jpg","show_account_transparency_details":true,"service":"instagram"},{"id":"1682023762","username":"saana_wahab","type":false,"fbid_v2":"17841401192886281","rest_id":"1807275099","full_name":"Sana Wahab","is_private":true,"post_count":false,"is_unpublished":false,"profile_picture":"https:\/\/b8fd-2603-3-610c-1060-00.ngrok-free.app\/media\/instagram_profile_pic\/8e29707e-32ed-4b65-b859-86c14314266e.jpg","show_account_transparency_details":true,"service":"instagram"},{"id":"1682023762","username":"qalamkar_interiors","type":false,"fbid_v2":"17841401192886281","rest_id":"9049709845","full_name":"Qalamkar Interiors","is_private":true,"post_count":false,"is_unpublished":false,"profile_picture":"https:\/\/b8fd-2603-3-610c-1060-00.ngrok-free.app\/media\/instagram_profile_pic\/3d18e7fb-5962-49d8-b2ef-e7d5da4ed8c7.jpg","show_account_transparency_details":true,"service":"instagram"},{"id":"1682023762","username":"mehwishjamil.yasir","type":false,"fbid_v2":"17841401192886281","rest_id":"1484740113","full_name":"Mehwish Yasir","is_private":true,"post_count":false,"is_unpublished":false,"profile_picture":"https:\/\/b8fd-2603-3-610c-1060-00.ngrok-free.app\/media\/instagram_profile_pic\/0ffaeab0-6ce4-4130-bd22-233477ff54de.jpg","show_account_transparency_details":true,"service":"instagram"},{"id":"1682023762","username":"saima_mansoor1","type":false,"fbid_v2":"17841401192886281","rest_id":"3245219116","full_name":"Saima Mansoor","is_private":true,"post_count":false,"is_unpublished":false,"profile_picture":"https:\/\/b8fd-2603-3-610c-1060-00.ngrok-free.app\/media\/instagram_profile_pic\/9d28c365-910f-483d-9031-ebb426dedcd8.jpg","show_account_transparency_details":true,"service":"instagram"},{"id":"1682023762","username":"nylabashir","type":false,"fbid_v2":"17841401192886281","rest_id":"5368927055","full_name":"Nyla Bashir","is_private":false,"post_count":false,"is_unpublished":false,"profile_picture":"https:\/\/b8fd-2603-3-610c-1060-00.ngrok-free.app\/media\/instagram_profile_pic\/0dea6d21-4b86-4f32-adf3-76487130caa8.jpg","show_account_transparency_details":true,"service":"instagram"},{"id":"1682023762","username":"raheelagauhar","type":false,"fbid_v2":"17841401192886281","rest_id":"283144876","full_name":"Raheela Gauhar","is_private":true,"post_count":false,"is_unpublished":false,"profile_picture":"https:\/\/b8fd-2603-3-610c-1060-00.ngrok-free.app\/media\/instagram_profile_pic\/83a1d1d5-703a-49b6-a51e-ec9994c1af32.jpg","show_account_transparency_details":true,"service":"instagram"},{"id":"1682023762","username":"sulemansaba","type":false,"fbid_v2":"17841401192886281","rest_id":"1542032985","full_name":"Saba Suleman","is_private":true,"post_count":false,"is_unpublished":false,"profile_picture":"https:\/\/b8fd-2603-3-610c-1060-00.ngrok-free.app\/media\/instagram_profile_pic\/69d92a7f-32bb-49a8-af68-a1d85d5bb26f.jpg","show_account_transparency_details":true,"service":"instagram"},{"id":"1682023762","username":"yousafmasooma","type":false,"fbid_v2":"17841401192886281","rest_id":"5717360111","full_name":"Masooma Sohaib","is_private":true,"post_count":false,"is_unpublished":false,"profile_picture":"https:\/\/b8fd-2603-3-610c-1060-00.ngrok-free.app\/media\/instagram_profile_pic\/da8ef91b-002f-4994-babe-9d1b71bb2c3a.jpg","show_account_transparency_details":true,"service":"instagram"},{"id":"1682023762","username":"minahill_salman","type":false,"fbid_v2":"17841401192886281","rest_id":"1637110051","full_name":"Anam Arshad","is_private":true,"post_count":false,"is_unpublished":false,"profile_picture":"https:\/\/b8fd-2603-3-610c-1060-00.ngrok-free.app\/media\/instagram_profile_pic\/98a081bb-002b-49aa-86eb-f17f8fb765a4.jpg","show_account_transparency_details":true,"service":"instagram"},{"id":"1682023762","username":"saniaali_40","type":false,"fbid_v2":"17841401192886281","rest_id":"49534630744","full_name":"Sania Ali","is_private":true,"post_count":false,"is_unpublished":false,"profile_picture":"https:\/\/b8fd-2603-3-610c-1060-00.ngrok-free.app\/media\/instagram_profile_pic\/37d3959f-4448-44dd-a5cb-5c268855725d.jpg","show_account_transparency_details":true,"service":"instagram"},{"id":"1682023762","username":"maha2410","type":false,"fbid_v2":"17841401192886281","rest_id":"241550824","full_name":"maha mansoor","is_private":true,"post_count":false,"is_unpublished":false,"profile_picture":"https:\/\/b8fd-2603-3-610c-1060-00.ngrok-free.app\/media\/instagram_profile_pic\/06ebb788-5b2c-409d-bfe6-7f22b881ed11.jpg","show_account_transparency_details":true,"service":"instagram"},{"id":"1682023762","username":"anayaahoor","type":false,"fbid_v2":"17841401192886281","rest_id":"8294705007","full_name":"Shiza Umair","is_private":true,"post_count":false,"is_unpublished":false,"profile_picture":"https:\/\/b8fd-2603-3-610c-1060-00.ngrok-free.app\/media\/instagram_profile_pic\/b33c1c46-9805-4db7-b974-75a58df45553.jpg","show_account_transparency_details":true,"service":"instagram"},{"id":"1682023762","username":"mashal_me","type":false,"fbid_v2":"17841401192886281","rest_id":"2435565626","full_name":"Mashal Imran","is_private":true,"post_count":false,"is_unpublished":false,"profile_picture":"https:\/\/b8fd-2603-3-610c-1060-00.ngrok-free.app\/media\/instagram_profile_pic\/d01e6122-03e4-43da-888b-effd241732ca.jpg","show_account_transparency_details":true,"service":"instagram"},{"id":"1682023762","username":"noorulsaba07","type":false,"fbid_v2":"17841401192886281","rest_id":"236551089","full_name":"Noor Abdullah","is_private":true,"post_count":false,"is_unpublished":false,"profile_picture":"https:\/\/b8fd-2603-3-610c-1060-00.ngrok-free.app\/media\/instagram_profile_pic\/94a8cbaa-bfe5-409c-b8f1-64e5a7fd0c25.jpg","show_account_transparency_details":true,"service":"instagram"},{"id":"1682023762","username":"eastbridgebysumera","type":false,"fbid_v2":"17841401192886281","rest_id":"59902362490","full_name":"Sumaira Naeem","is_private":false,"post_count":false,"is_unpublished":false,"profile_picture":"https:\/\/b8fd-2603-3-610c-1060-00.ngrok-free.app\/media\/instagram_profile_pic\/8f2e5f9a-f513-4302-96ae-3957eeeeb1b0.jpg","show_account_transparency_details":true,"service":"instagram"},{"id":"1682023762","username":"hinaamir100","type":false,"fbid_v2":"17841401192886281","rest_id":"3256564919","full_name":"Hina Amir","is_private":true,"post_count":false,"is_unpublished":false,"profile_picture":"https:\/\/b8fd-2603-3-610c-1060-00.ngrok-free.app\/media\/instagram_profile_pic\/63f4bf67-1941-4419-a4d8-6e9c18c2ffc3.jpg","show_account_transparency_details":true,"service":"instagram"},{"id":"1682023762","username":"shafiquemarjan","type":false,"fbid_v2":"17841401192886281","rest_id":"45439335787","full_name":"Marjan Shafique","is_private":false,"post_count":false,"is_unpublished":false,"profile_picture":"https:\/\/b8fd-2603-3-610c-1060-00.ngrok-free.app\/media\/instagram_profile_pic\/638c968a-53e2-4136-bfc3-45eb1c5f67eb.jpg","show_account_transparency_details":true,"service":"instagram"},{"id":"1682023762","username":"amna.waqas686","type":false,"fbid_v2":"17841401192886281","rest_id":"56009938800","full_name":"Amna Waqas","is_private":true,"post_count":false,"is_unpublished":false,"profile_picture":"https:\/\/b8fd-2603-3-610c-1060-00.ngrok-free.app\/media\/instagram_profile_pic\/3e675c75-058a-4a62-a3a9-b6ceace68bf2.jpg","show_account_transparency_details":true,"service":"instagram"},{"id":"1682023762","username":"afia_saad","type":false,"fbid_v2":"17841401192886281","rest_id":"767909855","full_name":"Afia Saad","is_private":true,"post_count":false,"is_unpublished":false,"profile_picture":"https:\/\/b8fd-2603-3-610c-1060-00.ngrok-free.app\/media\/instagram_profile_pic\/a232041a-ba7c-4a67-ba59-5f26b32268e6.jpg","show_account_transparency_details":true,"service":"instagram"},{"id":"1682023762","username":"maria_dogar","type":false,"fbid_v2":"17841401192886281","rest_id":"2303867796","full_name":"\ud83e\uddff    Maria Dogar","is_private":true,"post_count":false,"is_unpublished":false,"profile_picture":"https:\/\/b8fd-2603-3-610c-1060-00.ngrok-free.app\/media\/instagram_profile_pic\/e00aff19-1ba6-4e41-8dc4-76ccd0981f25.jpg","show_account_transparency_details":true,"service":"instagram"},{"id":"1682023762","username":"sonia.usman.71","type":false,"fbid_v2":"17841401192886281","rest_id":"8368354197","full_name":"Sonia Usman","is_private":true,"post_count":false,"is_unpublished":false,"profile_picture":"https:\/\/b8fd-2603-3-610c-1060-00.ngrok-free.app\/media\/instagram_profile_pic\/82707568-f1af-41dd-bcbf-a95f3a37f416.jpg","show_account_transparency_details":true,"service":"instagram"},{"id":"1682023762","username":"mona.asif116","type":false,"fbid_v2":"17841401192886281","rest_id":"6286234326","full_name":"Mona Asif","is_private":true,"post_count":false,"is_unpublished":false,"profile_picture":"https:\/\/b8fd-2603-3-610c-1060-00.ngrok-free.app\/media\/instagram_profile_pic\/96277834-3d8d-4eaa-b063-fa42ba186c1b.jpg","show_account_transparency_details":true,"service":"instagram"},{"id":"1682023762","username":"nimra7254","type":false,"fbid_v2":"17841401192886281","rest_id":"21666868088","full_name":"Nimra Asif","is_private":true,"post_count":false,"is_unpublished":false,"profile_picture":"https:\/\/b8fd-2603-3-610c-1060-00.ngrok-free.app\/media\/instagram_profile_pic\/185b0f90-cc22-4fde-9210-0eef7a1c43e5.jpg","show_account_transparency_details":true,"service":"instagram"},{"id":"1682023762","username":"hania.javed","type":false,"fbid_v2":"17841401192886281","rest_id":"1523219936","full_name":"Hania","is_private":true,"post_count":false,"is_unpublished":false,"profile_picture":"https:\/\/b8fd-2603-3-610c-1060-00.ngrok-free.app\/media\/instagram_profile_pic\/866f81f6-d8ce-42de-a456-cb892fceae45.jpg","show_account_transparency_details":true,"service":"instagram"},{"id":"1682023762","username":"nashiah647","type":false,"fbid_v2":"17841401192886281","rest_id":"601153421","full_name":"","is_private":true,"post_count":false,"is_unpublished":false,"profile_picture":"https:\/\/b8fd-2603-3-610c-1060-00.ngrok-free.app\/media\/instagram_profile_pic\/705f3cd5-dfa8-4781-a8e4-a16c01b8486c.jpg","show_account_transparency_details":true,"service":"instagram"},{"id":"1682023762","username":"ayesha_6181","type":false,"fbid_v2":"17841401192886281","rest_id":"7061936706","full_name":"ayesha nadeem","is_private":true,"post_count":false,"is_unpublished":false,"profile_picture":"https:\/\/b8fd-2603-3-610c-1060-00.ngrok-free.app\/media\/instagram_profile_pic\/1dff6e97-01ec-414a-9f4a-f536619c9ebe.jpg","show_account_transparency_details":true,"service":"instagram"},{"id":"1682023762","username":"hiraghaffar","type":false,"fbid_v2":"17841401192886281","rest_id":"639191758","full_name":"Hira Ghaffar","is_private":true,"post_count":false,"is_unpublished":false,"profile_picture":"https:\/\/b8fd-2603-3-610c-1060-00.ngrok-free.app\/media\/instagram_profile_pic\/32c7d033-6647-4066-868b-55e3e360df40.jpg","show_account_transparency_details":true,"service":"instagram"},{"id":"1682023762","username":"rashidnazia71","type":false,"fbid_v2":"17841401192886281","rest_id":"6980578658","full_name":"Nazia Rashid","is_private":true,"post_count":false,"is_unpublished":false,"profile_picture":"https:\/\/b8fd-2603-3-610c-1060-00.ngrok-free.app\/media\/instagram_profile_pic\/aba27cd4-eb2b-4b3e-a8c2-5a82082761ba.jpg","show_account_transparency_details":true,"service":"instagram"},{"id":"1682023762","username":"usman_ikram486","type":false,"fbid_v2":"17841401192886281","rest_id":"1551164156","full_name":"Usman Ikram","is_private":true,"post_count":false,"is_unpublished":false,"profile_picture":"https:\/\/b8fd-2603-3-610c-1060-00.ngrok-free.app\/media\/instagram_profile_pic\/b930eac0-96e0-4685-9189-375d7a4bca58.jpg","show_account_transparency_details":true,"service":"instagram"},{"id":"1682023762","username":"mehzeen_rameesh","type":false,"fbid_v2":"17841401192886281","rest_id":"63899381247","full_name":"Mehzeen","is_private":true,"post_count":false,"is_unpublished":false,"profile_picture":"https:\/\/b8fd-2603-3-610c-1060-00.ngrok-free.app\/media\/instagram_profile_pic\/9d1a59ce-86f8-411c-811b-fac3e7955dc6.jpg","show_account_transparency_details":true,"service":"instagram"},{"id":"1682023762","username":"dashinggirl1188","type":false,"fbid_v2":"17841401192886281","rest_id":"2965819904","full_name":"A.As","is_private":true,"post_count":false,"is_unpublished":false,"profile_picture":"https:\/\/b8fd-2603-3-610c-1060-00.ngrok-free.app\/media\/instagram_profile_pic\/fa2ae21e-2f46-4c0a-92b4-57847be2561a.jpg","show_account_transparency_details":true,"service":"instagram"},{"id":"1682023762","username":"sadia_78909","type":false,"fbid_v2":"17841401192886281","rest_id":"3578818337","full_name":"S\ud83c\udd70\ufe0fD\u2139\ud83c\udd70\ufe0f","is_private":false,"post_count":false,"is_unpublished":false,"profile_picture":"https:\/\/b8fd-2603-3-610c-1060-00.ngrok-free.app\/media\/instagram_profile_pic\/2b4ff7aa-8155-47dc-b4f1-dcbed96af099.jpg","show_account_transparency_details":true,"service":"instagram"},{"id":"1682023762","username":"hira_liaquat63","type":false,"fbid_v2":"17841401192886281","rest_id":"1294955485","full_name":"Hira Hamza","is_private":true,"post_count":false,"is_unpublished":false,"profile_picture":"https:\/\/b8fd-2603-3-610c-1060-00.ngrok-free.app\/media\/instagram_profile_pic\/30d63334-b205-4bcd-a5bf-6685c8ae2f9b.jpg","show_account_transparency_details":true,"service":"instagram"},{"id":"1682023762","username":"amnajavaid7","type":false,"fbid_v2":"17841401192886281","rest_id":"768812400","full_name":"Amna Javaid","is_private":true,"post_count":false,"is_unpublished":false,"profile_picture":"https:\/\/b8fd-2603-3-610c-1060-00.ngrok-free.app\/media\/instagram_profile_pic\/14532f2e-e062-41ea-8d00-6af9142774d5.jpg","show_account_transparency_details":true,"service":"instagram"},{"id":"1682023762","username":"hajrakhurram","type":false,"fbid_v2":"17841401192886281","rest_id":"1677518482","full_name":"Hajra Khurram","is_private":true,"post_count":false,"is_unpublished":false,"profile_picture":"https:\/\/b8fd-2603-3-610c-1060-00.ngrok-free.app\/media\/instagram_profile_pic\/bfa80cda-adbb-49b5-a28a-8ca6f49de405.jpg","show_account_transparency_details":true,"service":"instagram"},{"id":"1682023762","username":"sumerabehzad","type":false,"fbid_v2":"17841401192886281","rest_id":"1820335134","full_name":"Sumera Behzad","is_private":true,"post_count":false,"is_unpublished":false,"profile_picture":"https:\/\/b8fd-2603-3-610c-1060-00.ngrok-free.app\/media\/instagram_profile_pic\/98835057-7ba6-4838-9613-699c4122cb4c.jpg","show_account_transparency_details":true,"service":"instagram"},{"id":"1682023762","username":"anniekhalid12","type":false,"fbid_v2":"17841401192886281","rest_id":"2019670264","full_name":"Annie Asim","is_private":true,"post_count":false,"is_unpublished":false,"profile_picture":"https:\/\/b8fd-2603-3-610c-1060-00.ngrok-free.app\/media\/instagram_profile_pic\/df2be873-1fb5-49c2-9468-dc8a198b7341.jpg","show_account_transparency_details":true,"service":"instagram"},{"id":"1682023762","username":"rabiahamid1","type":false,"fbid_v2":"17841401192886281","rest_id":"4585823633","full_name":"Rabia Hamid","is_private":true,"post_count":false,"is_unpublished":false,"profile_picture":"https:\/\/b8fd-2603-3-610c-1060-00.ngrok-free.app\/media\/instagram_profile_pic\/e4fbbc04-fbcf-4f05-aef4-9435d6091580.jpg","show_account_transparency_details":true,"service":"instagram"},{"id":"1682023762","username":"nooramjadd","type":false,"fbid_v2":"17841401192886281","rest_id":"1476881121","full_name":"Noor Amjad","is_private":true,"post_count":false,"is_unpublished":false,"profile_picture":"https:\/\/b8fd-2603-3-610c-1060-00.ngrok-free.app\/media\/instagram_profile_pic\/4ae0dcbf-34fb-4842-b99e-6274e569a652.jpg","show_account_transparency_details":true,"service":"instagram"},{"id":"1682023762","username":"noorhira.sethi","type":false,"fbid_v2":"17841401192886281","rest_id":"1450493241","full_name":"Noor Ahmed","is_private":true,"post_count":false,"is_unpublished":false,"profile_picture":"https:\/\/b8fd-2603-3-610c-1060-00.ngrok-free.app\/media\/instagram_profile_pic\/c2b39e8a-e293-4e2b-bad7-4ea3295651c1.jpg","show_account_transparency_details":true,"service":"instagram"},{"id":"1682023762","username":"laline6688","type":false,"fbid_v2":"17841401192886281","rest_id":"61418236807","full_name":"Laline ,...","is_private":true,"post_count":false,"is_unpublished":false,"profile_picture":"https:\/\/b8fd-2603-3-610c-1060-00.ngrok-free.app\/media\/instagram_profile_pic\/17a30b5f-d35a-4c27-b4ee-148271df526f.jpg","show_account_transparency_details":true,"service":"instagram"}]